simplecalculator/__init__.py
simplecalculator/simplemodule.py
pelangikalku12-0.1.dist-info/LICENCE
pelangikalku12-0.1.dist-info/METADATA
pelangikalku12-0.1.dist-info/WHEEL
pelangikalku12-0.1.dist-info/top_level.txt
pelangikalku12-0.1.dist-info/RECORD
