Metadata-Version: 2.1
Name: pelangikalku12
Version: 0.1
Summary: Simplecalculator yang membuat pusing.
Home-page: https://github.com/codewithun/simplecalculator
Author: Untara Saputra
Author-email: untara337@example.com
License: MIT
License-File: LICENCE
